capella_diff_tools/__init__.py
capella_diff_tools/__main__.py
capella_diff_tools/compare.py
capella_diff_tools/report.html.jinja
capella_diff_tools/report.py
capella_diff_tools/types.py
capella_diff_tools-1.2.0.dist-info/licenses/LICENSES/Apache-2.0.txt
capella_diff_tools-1.2.0.dist-info/licenses/LICENSES/CC0-1.0.txt
capella_diff_tools-1.2.0.dist-info/METADATA
capella_diff_tools-1.2.0.dist-info/WHEEL
capella_diff_tools-1.2.0.dist-info/entry_points.txt
capella_diff_tools-1.2.0.dist-info/top_level.txt
capella_diff_tools-1.2.0.dist-info/RECORD
