Metadata-Version: 2.4
Name: capella-diff-tools
Version: 1.2.0
Summary: Tools for comparing different versions of a Capella model
Author: DB InfraGO AG
License-Expression: Apache-2.0
Project-URL: Homepage, https://github.com/DSD-DBS/capella-diff-tools
Project-URL: Documentation, https://dsd-dbs.github.io/capella-diff-tools
Platform: any
Classifier: Development Status :: 4 - Beta
Classifier: Natural Language :: English
Classifier: Operating System :: OS Independent
Classifier: Programming Language :: Python :: 3 :: Only
Classifier: Programming Language :: Python :: 3.11
Classifier: Programming Language :: Python :: 3.12
Classifier: Programming Language :: Python :: 3.13
Requires-Python: <3.14,>=3.11
License-File: LICENSES/Apache-2.0.txt
License-File: LICENSES/CC0-1.0.txt
Requires-Dist: capellambse<0.7,>=0.6.6
Requires-Dist: click
Requires-Dist: diff-match-patch>=20230430
Requires-Dist: jinja2>=3.1.2
Requires-Dist: pyyaml>=6.0.1
Provides-Extra: docs
Requires-Dist: furo; extra == "docs"
Requires-Dist: sphinx; extra == "docs"
Requires-Dist: sphinx-copybutton; extra == "docs"
Requires-Dist: tomli; python_version < "3.11" and extra == "docs"
Provides-Extra: test
Requires-Dist: pytest; extra == "test"
Requires-Dist: pytest-cov; extra == "test"
Dynamic: license-file
